kfst_rs-0.2.5.dist-info/METADATA
kfst_rs-0.2.5.dist-info/WHEEL
kfst_rs/__init__.py
kfst_rs/kfst_rs.abi3.so
kfst_rs-0.2.5.dist-info/RECORD
