Metadata-Version: 2.4
Name: kfst-rs
Version: 0.2.5
Classifier: Programming Language :: Rust
Classifier: Programming Language :: Python :: Implementation :: CPython
Classifier: Programming Language :: Python :: Implementation :: PyPy
Summary: The accelerated companion library to kfst
Keywords: finnish,nlp,morphology,rust
Author-email: Théo Salmenkivi-Friberg <theo.friberg@helsinki.fi>, Iikka Hauhio <iikka.hauhio@helsinki.fi>
License-Expression: LGPL-3.0-or-later
Requires-Python: >=3.11
Project-URL: Bug Tracker, https://github.com/fergusq/fst-python/issues
Project-URL: Homepage, https://github.com/fergusq/fst-python
Project-URL: Repository, https://github.com/fergusq/fst-python
